{
    "1": {
        "channel": 1, 
        "defs": {
            "blue": 5, 
            "dimmer": 1, 
            "green": 4, 
            "red": 3
        }, 
        "inits": {
            "blue": 253, 
            "dimmer": 255, 
            "green": 130, 
            "red": 255
        }, 
        "knobs": {
            "blue": {
                "fgColor": "blue"
            }, 
            "dimmer": {
                "cursor": 40, 
                "fgColor": "yellow"
            }, 
            "green": {
                "fgColor": "green"
            }, 
            "red": {
                "fgColor": "red"
            }
        }
    }, 
    "2": {
        "channel": 10, 
        "defs": {
            "blue": 5, 
            "dimmer": 1, 
            "green": 4, 
            "red": 3
        }, 
        "inits": {
            "blue": 253, 
            "dimmer": 255, 
            "green": 130, 
            "red": 255
        }, 
        "knobs": {
            "blue": {
                "fgColor": "blue"
            }, 
            "dimmer": {
                "cursor": 40, 
                "fgColor": "yellow"
            }, 
            "green": {
                "fgColor": "green"
            }, 
            "red": {
                "fgColor": "red"
            }
        }
    }
}